pyams_zmi/__init__.py
pyams_zmi/configuration.py
pyams_zmi/factory.py
pyams_zmi/form.py
pyams_zmi/include.py
pyams_zmi/profile.py
pyams_zmi/rest.py
pyams_zmi/search.py
pyams_zmi/skin.py
pyams_zmi/table.py
pyams_zmi/utils.py
pyams_zmi/view.py
pyams_zmi/doctests/README.rst
pyams_zmi/doctests/rest.rst
pyams_zmi/generations/__init__.py
pyams_zmi/generations/zodbupdate.py
pyams_zmi/helper/__init__.py
pyams_zmi/helper/container.py
pyams_zmi/helper/event.py
pyams_zmi/interfaces/__init__.py
pyams_zmi/interfaces/configuration.py
pyams_zmi/interfaces/form.py
pyams_zmi/interfaces/profile.py
pyams_zmi/interfaces/table.py
pyams_zmi/interfaces/viewlet.py
pyams_zmi/interfaces/templates/admin-layout.pt
pyams_zmi/interfaces/templates/form-checker.pt
pyams_zmi/interfaces/templates/form-display.pt
pyams_zmi/interfaces/templates/form-group.pt
pyams_zmi/interfaces/templates/form-switcher.pt
pyams_zmi/interfaces/templates/form-tabform.pt
pyams_zmi/interfaces/templates/form.pt
pyams_zmi/interfaces/templates/inner-table-empty.pt
pyams_zmi/interfaces/templates/inner-table.pt
pyams_zmi/interfaces/templates/search-view.pt
pyams_zmi/interfaces/templates/table-empty.pt
pyams_zmi/interfaces/templates/table-multiple.pt
pyams_zmi/interfaces/templates/table-switcher.pt
pyams_zmi/interfaces/templates/table.pt
pyams_zmi/locales/pyams_zmi.pot
pyams_zmi/locales/fr/LC_MESSAGES/pyams_zmi.mo
pyams_zmi/locales/fr/LC_MESSAGES/pyams_zmi.po
pyams_zmi/tests/__init__.py
pyams_zmi/tests/test_utilsdocs.py
pyams_zmi/tests/test_utilsdocstrings.py
pyams_zmi/zmi/__init__.py
pyams_zmi/zmi/breadcrumb.py
pyams_zmi/zmi/configuration.py
pyams_zmi/zmi/controlpanel.py
pyams_zmi/zmi/environment.py
pyams_zmi/zmi/interfaces.py
pyams_zmi/zmi/metas.py
pyams_zmi/zmi/profile.py
pyams_zmi/zmi/registry.py
pyams_zmi/zmi/resources.py
pyams_zmi/zmi/skin.py
pyams_zmi/zmi/swagger.py
pyams_zmi/zmi/timezone.py
pyams_zmi/zmi/resources/css/swagger-ui.css
pyams_zmi/zmi/resources/css/swagger-ui.min.css
pyams_zmi-2.6.2.dist-info/LICENSE
pyams_zmi-2.6.2.dist-info/METADATA
pyams_zmi-2.6.2.dist-info/WHEEL
pyams_zmi-2.6.2.dist-info/entry_points.txt
pyams_zmi-2.6.2.dist-info/namespace_packages.txt
pyams_zmi-2.6.2.dist-info/top_level.txt
pyams_zmi-2.6.2.dist-info/RECORD
