Metadata-Version: 2.1
Name: pyams-zmi
Version: 2.6.2
Summary: PyAMS management interface package
Home-page: https://pyams.readthedocs.io
Author: Thierry Florac
Author-email: tflorac@ulthar.net
License: ZPL
Keywords: Pyramid PyAMS
Classifier: License :: OSI Approved :: Zope Public License
Classifier: Development Status :: 4 - Beta
Classifier: Programming Language :: Python
Classifier: Framework :: Pyramid
Classifier: Topic :: Software Development :: Libraries :: Python Modules
Requires-Python: >=3.7
License-File: LICENSE
Requires-Dist: setuptools
Requires-Dist: cornice
Requires-Dist: cornice-swagger
Requires-Dist: myams-js>=2.5.0
Requires-Dist: persistent
Requires-Dist: pyams-file
Requires-Dist: pyams-form>=2.1.0
Requires-Dist: pyams-i18n
Requires-Dist: pyams-layer
Requires-Dist: pyams-pagelet
Requires-Dist: pyams-security>=1.8.1
Requires-Dist: pyams-site
Requires-Dist: pyams-skin>=2.2.0
Requires-Dist: pyams-table>=1.3.1
Requires-Dist: pyams-template
Requires-Dist: pyams-utils
Requires-Dist: pyams-viewlet
Requires-Dist: pyramid>=2.0.0
Requires-Dist: zope.component
Requires-Dist: zope.container
Requires-Dist: zope.contentprovider
Requires-Dist: zope.dublincore
Requires-Dist: zope.interface
Requires-Dist: zope.location
Requires-Dist: zope.schema
Requires-Dist: importlib-metadata; python_version < "3.8"
Provides-Extra: test
Requires-Dist: pyams-file; extra == "test"
Requires-Dist: pyramid-zcml; extra == "test"
Requires-Dist: zope.exceptions; extra == "test"
